benchmarks_app/__init__.py
benchmarks_app/admin.py
benchmarks_app/apps.py
benchmarks_app/drest.py
benchmarks_app/drf.py
benchmarks_app/models.py
benchmarks_app/tests.py
benchmarks_app/views.py
benchmarks_app/migrations/0001_initial.py
benchmarks_app/migrations/__init__.py
dynamic_rest/__init__.py
dynamic_rest/apps.py
dynamic_rest/bases.py
dynamic_rest/compat.py
dynamic_rest/conf.py
dynamic_rest/constants.py
dynamic_rest/datastructures.py
dynamic_rest/links.py
dynamic_rest/meta.py
dynamic_rest/metadata.py
dynamic_rest/pagination.py
dynamic_rest/paginator.py
dynamic_rest/prefetch.py
dynamic_rest/processors.py
dynamic_rest/related.py
dynamic_rest/renderers.py
dynamic_rest/routers.py
dynamic_rest/serializers.py
dynamic_rest/tagged.py
dynamic_rest/utils.py
dynamic_rest/viewsets.py
dynamic_rest/blueprints/__deprecated__
dynamic_rest/blueprints/api/__init__.py
dynamic_rest/blueprints/api/context.py
dynamic_rest/blueprints/api/templates/{{app}}/__init__.py.j2
dynamic_rest/blueprints/api/templates/{{app}}/api/__init__.py.j2
dynamic_rest/blueprints/api/templates/{{app}}/api/urls.py.j2
dynamic_rest/blueprints/api/templates/{{app}}/api/{{version}}/__init__.py.j2
dynamic_rest/blueprints/api/templates/{{app}}/api/{{version}}/urls.py.j2
dynamic_rest/blueprints/api/templates/{{app}}/api/{{version}}/serializers/__init__.py.j2
dynamic_rest/blueprints/api/templates/{{app}}/api/{{version}}/serializers/base.py.j2
dynamic_rest/blueprints/api/templates/{{app}}/api/{{version}}/serializers/{{name}}.py.j2
dynamic_rest/blueprints/api/templates/{{app}}/api/{{version}}/views/__init__.py.j2
dynamic_rest/blueprints/api/templates/{{app}}/api/{{version}}/views/base.py.j2
dynamic_rest/blueprints/api/templates/{{app}}/api/{{version}}/views/{{name}}.py.j2
dynamic_rest/blueprints/init/__init__.py
dynamic_rest/blueprints/init/context.py
dynamic_rest/blueprints/init/templates/{{app}}/settings.py.j2
dynamic_rest/fields/__init__.py
dynamic_rest/fields/common.py
dynamic_rest/fields/fields.py
dynamic_rest_bse-2.5.3.dist-info/licenses/LICENSE.md
dynamic_rest_bse-2.5.3.dist-info/licenses/LICENSE.txt
dynamic_rest_bse-2.5.3.dist-info/METADATA
dynamic_rest_bse-2.5.3.dist-info/WHEEL
dynamic_rest_bse-2.5.3.dist-info/top_level.txt
dynamic_rest_bse-2.5.3.dist-info/RECORD
