Metadata-Version: 2.4
Name: dynamic-rest-bse
Version: 2.5.3
Summary: Dynamic API support to Django REST Framework. Forked...
Home-page: http://github.com/BillSchumacher/dynamic-rest
Classifier: Framework :: Django
Classifier: Intended Audience :: Developers
Classifier: License :: OSI Approved :: BSD License
Classifier: Programming Language :: Python
Classifier: Programming Language :: Python :: 3
Classifier: Programming Language :: Python :: 3.9
Classifier: Programming Language :: Python :: 3.10
Classifier: Programming Language :: Python :: 3.11
Classifier: Programming Language :: Python :: 3.12
Classifier: Topic :: Software Development :: Libraries :: Python Modules
License-File: LICENSE.md
License-File: LICENSE.txt
Requires-Dist: Django<5.2,>=3.2
Requires-Dist: djangorestframework<3.17,>=3.11.2
Requires-Dist: inflection>=0.5.0
Requires-Dist: requests
Requires-Dist: sqids>=0.1.0
Requires-Dist: orjson>=3.9.7
Dynamic: classifier
Dynamic: description
Dynamic: description-content-type
Dynamic: home-page
Dynamic: license-file
Dynamic: requires-dist
Dynamic: summary
